polisan_plugin
