Metadata-Version: 2.1
Name: polisan-plugin
Version: 0.0.8
Summary: Use this lib to build your plugins to polisan servers
Home-page: UNKNOWN
Author: LandaM
Author-email: qwer.009771@gmail.com
License: MIT
Platform: UNKNOWN
